{"stats":{"minecraft:used":{"minecraft:netherite_sword":33,"atmosphere:raw_luminum_block":5,"atmosphere:saint_spawn_egg":19,"atmosphere:witch_pool":1,"atmosphere:balloon_fly_spawn_egg":17,"atmosphere:witch_crushing_stone":2,"minecraft:grass_block":4,"atmosphere:luminum_block":7,"atmosphere:tub":1,"geckolib3:habitat":2,"atmosphere:rayven_spawn_egg":4,"minecraft:spruce_sign":1,"geckolib3:fertilizer":2},"minecraft:killed":{"atmosphere:saint":13,"atmosphere:balloon_fly":9},"minecraft:killed_by":{"atmosphere:saint":2},"minecraft:picked_up":{"minecraft:netherite_sword":1},"minecraft:custom":{"minecraft:time_since_rest":12186,"minecraft:crouch_one_cm":326,"minecraft:deaths":2,"minecraft:sprint_one_cm":15704,"minecraft:play_time":26235,"minecraft:walk_one_cm":49420,"minecraft:damage_taken":720,"minecraft:sneak_time":424,"minecraft:mob_kills":22,"minecraft:jump":108,"minecraft:damage_dealt":2320,"minecraft:leave_game":5,"minecraft:time_since_death":12161,"minecraft:total_world_time":62481,"minecraft:fly_one_cm":75589}},"DataVersion":3120}